pnums/__init__.py
pnums/int_to_xcoords.py
pnums/ith_middle.py
pnums/neuralfloat.py
pnums/p_int.py
pnums/xcoords_to_int.py
pnums-0.0.4.dist-info/LICENSE.md
pnums-0.0.4.dist-info/METADATA
pnums-0.0.4.dist-info/WHEEL
pnums-0.0.4.dist-info/top_level.txt
pnums-0.0.4.dist-info/RECORD
